{
  "name": "Adaptive Simple SMA 30",
  "underlying_symbol": "QQQ",
  "calculations": [
    {
      "name": "sma_30",
      "type": "SMA",
      "period": 30
    }
  ],
  "rules": [
    {
      "conditions": [
        {
          "calculation": "sma_30",
          "operator": "<=",
          "threshold": 0.0
        }
      ],
      "ticker": "QQQ"
    },
    {
      "conditions": [
        {
          "calculation": "sma_30",
          "operator": ">",
          "threshold": 0.0
        }
      ],
      "ticker": "TQQQ"
    }
  ]
}
